{
    "usedGiftCardsAmount":0,
    "id":"f540c2b6-1d46-46f5-a61c-2e75078c2856",
    "voucherStatus":[
    
    ],
    "subtotal":76990,
    "estimatedBestShippingPrice":0,
    "gifts":[
    
    ],
    "locale":{
        "locale":"pt-BR",
        "brazil":true,
        "country":"BRA",
        "notBrazil":false,
        "currencyCode":"BRL",
        "notCountryCOL":true,
        "countryCOL":false
    },
    "freightPrice":0,
    "giftCardsAmount":0,
    "bestInstallment":{
        "valuePerInstallment":76.98999999999999,
        "valuePerInstallmentCents":7699,
        "installmentAmount":10,
        "formattedValuePerInstallment":"76,99"
    },
    "hasError":true,
    "userProfile":{
        "visitorIdentity":"rXf8OUKsosS1xn2ARDqsnFfDctZ22MKFvFpfUcCsgWevQ8FvkM1dwNE007I4qmdRY6jZ7mx76E2ijoDO4v4S1g7JxZzNvAkilFNgyxB7Ogk=",
        "lastName":"Amalfi Vilasboas ",
        "firstName":"Jabna",
        "preferences":{
            "email":true,
            "sms":false,
            "acceptedTerm":false
        },
        "corporate":false,
        "dateBirth":"1980-02-28",
        "phones":[
                  {
                  "number":"353353535",
                  "areaCode":"11",
                  "type":"MOBILE"
                  },
                  {
                  "number":"32669098",
                  "areaCode":"11",
                  "type":"RESIDENTIAL"
                  },
                  {
                  "number":"11111111",
                  "areaCode":"11",
                  "type":"BUSINESS"
                  }
                  ],
        "fullName":"Jabna Amalfi Vilasboas ",
        "guid":"f540c2b6-1d46-46f5-a61c-2e75078c2856",
        "email":"jabna1@mobteste.net",
        "gender":"MALE",
        "document":"53218622735"
    },
    "freightPriceLocal":0,
    "chaordicInfo":{
        "cartSource":"cart",
        "apiKey":"walmart-marketplace",
        "cartCryptoContent":"\/qqxX4HZGg7mP+bzNbOyhUrq3vAPtaq82x0LsHNm500BgK1DvYkGfwd2amVaOhVpEsZoGD4v1BUpIPlhFtbb7eT5HiRFY78Os\/UXg8UnOoIay5kYHDiuHXpeQs\/n8oRrZ5Bk+FjE+yw4TXsaHeYbT2e\/r6owfFqeWQfFkaB2O3ki8vxhpNVLOyySzWt9g1kVIZbIrr2ldgE4jeK6UaVeDSegYh1oKaBcJ0NER5dQJsXlwK+PAhEUnTh0sGGvr9RQQcCuIJKKMJ4UAtjFoImP0jBFcIrhBW8LUWE\/OvmdRKzHd6kodlyaQpSlH7+jhO5kRmkd7z4UX0iWVaKfG3i\/LkncBWlQXW\/VFmybGM1XCtM6tuqF4UVZB9mjNfjTvf4l7DZgCAVLQ9kS+evn7GPLLw=="
    },
    "giftWrapperServicesAmount":0,
    "freightPriceImported":0,
    "giftCards":[
    
    ],
    "discountsAmount":0,
    "removedGiftCards":[
    
    ],
    "totalPriceWithEstimatedBestShipping":76990,
    "postalCode":"06485370",
    "couponAmount":0,
    "amounts":{
        "importFeesAmount":0,
        "totalAmount":76990,
        "totalAmountWithEstimatedBestShipping":76990,
        "totalAmountWithEstimatedBestShippingPlusGiftCardDiscountAmount":76990,
        "estimatedBestShippingAmountLocal":0,
        "estimatedBestShippingAmountImported":0,
        "usedNominalDiscount":0,
        "servicesAmount":0,
        "nominalDiscount":0,
        "giftCardsAmount":0,
        "remainingGiftCardsAmount":0,
        "totalAmountPlusGiftCardDiscountAmount":76990,
        "totalNominalDiscount":0,
        "estimatedBestShippingAmount":0,
        "productsAmount":76990,
        "couponAmount":0,
        "nominalDifference":0,
        "deliveriesAmount":0,
        "giftWrapperServicesAmount":0,
        "nominalFromCoupon":false,
        "discountsAmount":0,
        "giftCardDiscountAmount":0,
        "deliveriesAmountImported":0,
        "deliveriesAmountLocal":0,
        "usedGiftCardsAmount":0
    },
    "nominalDiscount":0,
    "loadOrderParams":"1,1058479",
    "servicesPriceWithGiftWrapper":0,
    "giftCardDiscountAmount":0,
    "servicesPrice":0,
    "loggerKey":"8n4dnjrebol4c4mkk77wu0d3v",
    "remainingGiftCardsAmount":0,
    "userLogged":true,
    "items":[
             {
             "productId":2945284,
             "kit":false,
             "priceWithoutDiscountCurrent":76990,
             "categoryId":728,
             "unavailableProduct":false,
             "departmentId":345,
             "service":false,
             "priceDivergentToLow":false,
             "priceDivergentToHigh":false,
             "markedToRemove":false,
             "description":"Bicicleta Dobrável Ozark Trail 6 Marchas, Aro 20, Freios V-Brake, Câmbio Shimano, Branca Fosco",
             "subCategoryId":353,
             "key":"65mgb2k11vtrybf9927m18rm2",
             "priceDivergent":false,
             "sellerId":"1",
             "errorCode":{
             "systemErrorId":"LGT0402",
             "errorLevel":"ITEM_LEVEL",
             "errorCode":"DELIVERY_NOT_POSSIBLE"
             },
             "services":[
             
             ],
             "isGiftWrapper":false,
             "defaultContext":{
             "departmentId":null,
             "subcategoryName":null,
             "subcategoryId":null,
             "categoryId":null,
             "categoryName":null,
             "departmentName":null
             },
             "itemUnavailable":false,
             "shippingValue":0,
             "sku":1058479,
             "servicesIds":[
             
             ],
             "quantity":1,
             "createDateTime":1458065389864,
             "price":76990,
             "comission":0,
             "brandName":"Ozark Trail",
             "originalImageUrl":"\/\/static.wmobjects.com.br\/imgres\/arquivos\/ids\/4012146",
             "cartImageUrl":"\/\/static.wmobjects.com.br\/imgres\/arquivos\/ids\/4012146",
             "detailUrl":"\/produto\/2945284\/pr",
             "marketPlaceSku":1058479,
             "giftWrappable":false,
             "skuName":"Bicicleta Dobrável Ozark Trail 6 Marchas, Aro 20, Freios V-Brake, Câmbio Shimano, Branca Fosco",
             "kitItems":[
             
             ],
             "deliveryTypes":[
             
             ],
             "imageUrl":"\/\/static.wmobjects.com.br\/imgres\/arquivos\/ids\/4012146",
             "sellerName":"Walmart",
             "categories":[
                           {
                           "id":345,
                           "name":"Esporte e Lazer"
                           },
                           {
                           "id":728,
                           "name":"Ciclismo e Bikes"
                           },
                           {
                           "id":353,
                           "name":"Bicicletas"
                           }
                           ],
             "fullDescription":"Bicicleta Dobrável Ozark Trail 6 Marchas, Aro 20, Freios V-Brake, Câmbio Shimano, Branca Fosco",
             "priceWithoutDiscountOriginal":76990,
             "pageContext":{  
             "departmentId":null,
             "subcategoryName":null,
             "subcategoryId":null,
             "categoryId":null,
             "categoryName":null,
             "departmentName":null
             },
             "importFee":0,
             "currentMaxQuantityBySellerAndSku":1,
             "listPrice":99990,
             "stockBalance":12
             }
             ],
    "totalPrice":76990,
    "hasProductImported":false
}